ganit/__init__.py
ganit/_baisc.py
ganit/setup.py
math/__init__.py
math/_basic.py
math/setup.py
packagesorry-0.1.2.dist-info/METADATA
packagesorry-0.1.2.dist-info/WHEEL
packagesorry-0.1.2.dist-info/top_level.txt
packagesorry-0.1.2.dist-info/RECORD
