Metadata-Version: 2.1
Name: packagesorry
Version: 0.1.2
Summary: This code with harry
Author: Harry
License: UNKNOWN
Platform: UNKNOWN
